{
  "id": "video-actor-extract-workflow",
  "revision": 1.0,
  "last_node_id": 3,
  "last_link_id": 1,
  "nodes": [
    {
      "id": 1,
      "type": "VideoActorExtractor",
      "pos": [
        100,
        100
      ],
      "size": [
        400,
        200
      ],
      "flags": {},
      "order": 0,
      "mode": 0,
      "inputs": [],
      "outputs": [
        {
          "name": "actor_info_json",
          "type": "STRING",
          "links": [
            1
          ],
          "shape": 3,
          "slot_index": 0
        },
        {
          "name": "output_dir",
          "type": "STRING",
          "links": null,
          "shape": 3
        }
      ],
      "properties": {
        "Node name for S&R": "VideoActorExtractor"
      },
      "widgets_values": [
        "",
        "yolov8n.pt",
        10,
        0.6,
        3,
        5
      ],
      "color": "#233",
      "bgcolor": "#355"
    },
    {
      "id": 2,
      "type": "Save Text File",
      "pos": [
        600,
        100
      ],
      "size": [
        400,
        178
      ],
      "flags": {},
      "order": 1,
      "mode": 0,
      "inputs": [
        {
          "name": "text",
          "type": "STRING",
          "link": 1,
          "widget": {
            "name": "text"
          }
        }
      ],
      "outputs": [],
      "properties": {
        "Node name for S&R": "Save Text File"
      },
      "widgets_values": [
        "./ComfyUI/output/[time(%Y-%m-%d)]",
        "actor_info",
        "_",
        4,
        ".txt",
        "utf-8",
        ""
      ]
    }
  ],
  "links": [
    [
      1,
      1,
      0,
      2,
      0,
      "STRING"
    ]
  ],
  "groups": [
    {
      "title": "Video Actor Extract",
      "bounding": [
        80,
        60,
        940,
        270
      ],
      "color": "#3f789e",
      "font_size": 24
    }
  ],
  "config": {},
  "extra": {
    "ds": {
      "scale": 1,
      "offset": [
        0,
        0
      ]
    },
    "frontendVersion": "1.37.11",
    "VHS_latentpreview": false,
    "VHS_latentpreviewrate": 0,
    "VHS_MetadataImage": true,
    "VHS_KeepIntermediate": true
  },
  "version": 0.4
}
